conwhat/__init__.py
conwhat/__main__.py
conwhat/_version.py
conwhat/atlas.py
conwhat/utils/__init__.py
conwhat/utils/fetchers.py
conwhat/utils/readers.py
conwhat/utils/stats.py
conwhat/viz/__init__.py
conwhat/viz/network.py
conwhat/viz/streams.py
conwhat/viz/volume.py
conwhat-0.1.2.dev0.dist-info/DESCRIPTION.rst
conwhat-0.1.2.dev0.dist-info/METADATA
conwhat-0.1.2.dev0.dist-info/RECORD
conwhat-0.1.2.dev0.dist-info/WHEEL
conwhat-0.1.2.dev0.dist-info/entry_points.txt
conwhat-0.1.2.dev0.dist-info/metadata.json
conwhat-0.1.2.dev0.dist-info/top_level.txt
