Metadata-Version: 2.0
Name: conwhat
Version: 0.1.2.dev0
Summary: python library for connectome-based white matter atlas analyses in neuroimaging
Home-page: https://github.com/JohnGriffiths/conwhat
Author: John David Griffiths
Author-email: j.davidgriffiths@gmail.com
License: UNKNOWN
Keywords: white matter,tractography,MRI,DTI,diffusion,python
Platform: UNKNOWN
Classifier: Intended Audience :: Science/Research
Classifier: Programming Language :: Python
Classifier: Topic :: Software Development
Classifier: Topic :: Scientific/Engineering
Classifier: Operating System :: Microsoft :: Windows
Classifier: Operating System :: POSIX
Classifier: Operating System :: Unix
Classifier: Operating System :: MacOS
Classifier: Programming Language :: Python :: 2.7
Classifier: Programming Language :: Python :: 3.6
Requires-Dist: dipy
Requires-Dist: indexed-gzip
Requires-Dist: joblib
Requires-Dist: matplotlib
Requires-Dist: networkx
Requires-Dist: nibabel
Requires-Dist: nilearn
Requires-Dist: numpy
Requires-Dist: pandas
Requires-Dist: pyyaml
Requires-Dist: setuptools
Requires-Dist: sklearn
